[
    {
        "text": "<@U061S4J2DSP> ",
        "files": [
            {
                "id": "F09FH7WJRMJ",
                "created": 1757978755,
                "timestamp": 1757978755,
                "name": "IMG_7513.jpg",
                "title": "IMG_7513",
                "mimetype": "image\/jpeg",
                "filetype": "jpg",
                "pretty_type": "JPEG",
                "user": "U0806A1C509",
                "user_team": "T0P9KU8UD",
                "editable": false,
                "size": 1982243,
                "mode": "hosted",
                "is_external": false,
                "external_type": "",
                "is_public": true,
                "public_url_shared": false,
                "display_as_bot": false,
                "username": "",
                "url_private": "https:\/\/files.slack.com\/files-pri\/T0P9KU8UD-F09FH7WJRMJ\/img_7513.jpg?token=xoxe-23325960965-9983715179761-9964412545267-7f7e21946507533879d0107de1674c00",
                "url_private_download": "https:\/\/files.slack.com\/files-pri\/T0P9KU8UD-F09FH7WJRMJ\/download\/img_7513.jpg?token=xoxe-23325960965-9983715179761-9964412545267-7f7e21946507533879d0107de1674c00",
                "media_display_type": "unknown",
                "thumb_64": "https:\/\/files.slack.com\/files-tmb\/T0P9KU8UD-F09FH7WJRMJ-1ecf25144f\/img_7513_64.jpg?t=xoxe-23325960965-9983715179761-9964412545267-7f7e21946507533879d0107de1674c00",
                "thumb_80": "https:\/\/files.slack.com\/files-tmb\/T0P9KU8UD-F09FH7WJRMJ-1ecf25144f\/img_7513_80.jpg?t=xoxe-23325960965-9983715179761-9964412545267-7f7e21946507533879d0107de1674c00",
                "thumb_360": "https:\/\/files.slack.com\/files-tmb\/T0P9KU8UD-F09FH7WJRMJ-1ecf25144f\/img_7513_360.jpg?t=xoxe-23325960965-9983715179761-9964412545267-7f7e21946507533879d0107de1674c00",
                "thumb_360_w": 270,
                "thumb_360_h": 360,
                "thumb_480": "https:\/\/files.slack.com\/files-tmb\/T0P9KU8UD-F09FH7WJRMJ-1ecf25144f\/img_7513_480.jpg?t=xoxe-23325960965-9983715179761-9964412545267-7f7e21946507533879d0107de1674c00",
                "thumb_480_w": 360,
                "thumb_480_h": 480,
                "thumb_160": "https:\/\/files.slack.com\/files-tmb\/T0P9KU8UD-F09FH7WJRMJ-1ecf25144f\/img_7513_160.jpg?t=xoxe-23325960965-9983715179761-9964412545267-7f7e21946507533879d0107de1674c00",
                "thumb_720": "https:\/\/files.slack.com\/files-tmb\/T0P9KU8UD-F09FH7WJRMJ-1ecf25144f\/img_7513_720.jpg?t=xoxe-23325960965-9983715179761-9964412545267-7f7e21946507533879d0107de1674c00",
                "thumb_720_w": 540,
                "thumb_720_h": 720,
                "thumb_800": "https:\/\/files.slack.com\/files-tmb\/T0P9KU8UD-F09FH7WJRMJ-1ecf25144f\/img_7513_800.jpg?t=xoxe-23325960965-9983715179761-9964412545267-7f7e21946507533879d0107de1674c00",
                "thumb_800_w": 800,
                "thumb_800_h": 1067,
                "thumb_960": "https:\/\/files.slack.com\/files-tmb\/T0P9KU8UD-F09FH7WJRMJ-1ecf25144f\/img_7513_960.jpg?t=xoxe-23325960965-9983715179761-9964412545267-7f7e21946507533879d0107de1674c00",
                "thumb_960_w": 720,
                "thumb_960_h": 960,
                "thumb_1024": "https:\/\/files.slack.com\/files-tmb\/T0P9KU8UD-F09FH7WJRMJ-1ecf25144f\/img_7513_1024.jpg?t=xoxe-23325960965-9983715179761-9964412545267-7f7e21946507533879d0107de1674c00",
                "thumb_1024_w": 768,
                "thumb_1024_h": 1024,
                "original_w": 4284,
                "original_h": 5712,
                "thumb_tiny": "AwAwACSCNgBgmp1PcYqqflAIzkCmhyAWxnBxQlcGy7RkL978apK7E\/L+XrUqwSSopyAhPUn3xSasNO49p4weuf1pPtEf+QaBZHn95+lL9iP\/AD0\/8dqboqzIGBCH0I\/lSIAYyBvySDwufWnNjcoIyBU8EMNxkgMMdhwKsgjUhYimXHXPy\/T39qnjO2KBMnrnn609bREcMGf6E8U9oVyGTAPX1qWUhuQevajIpuJATuXcfXP\/ANej5v8Ann\/n86RdyqiebKAvYZNXoUMZY56gDH5\/404AADA6DjinDFVczEJpKO9ITSATNGaQ9aKBn\/\/Z",
                "permalink": "https:\/\/cornelldti.slack.com\/files\/UNZJ5EE3A\/F09FH7WJRMJ\/img_7513.jpg",
                "permalink_public": "https:\/\/slack-files.com\/T0P9KU8UD-F09FH7WJRMJ-06bc559285",
                "is_starred": false,
                "skipped_shares": true,
                "has_rich_preview": false,
                "file_access": "visible"
            }
        ],
        "upload": false,
        "user": "U0806A1C509",
        "display_as_bot": false,
        "blocks": [
            {
                "type": "rich_text",
                "block_id": "umID9",
                "elements": [
                    {
                        "type": "rich_text_section",
                        "elements": [
                            {
                                "type": "user",
                                "user_id": "U061S4J2DSP"
                            },
                            {
                                "type": "text",
                                "text": " "
                            }
                        ]
                    }
                ]
            }
        ],
        "type": "message",
        "ts": "1757978804.266669",
        "client_msg_id": "22B64743-B382-48CE-96C1-4EB929C41387",
        "reactions": [
            {
                "name": "cat-dance",
                "users": [
                    "U06KNF03QKB",
                    "U06KBGE3LGK",
                    "U04Q99S2Y3C",
                    "U0800DE2GPN",
                    "U0806411Z5X",
                    "U06KAR47ZR9"
                ],
                "count": 6
            },
            {
                "name": "lock",
                "users": [
                    "U061S4J2DSP",
                    "U0806411Z5X",
                    "U080G6QDZT2",
                    "U05T51X984Q",
                    "U08E3UQ7BGB"
                ],
                "count": 5
            }
        ]
    }
]