[
    {
        "text": "methinks this is <@U080M7935R6> no beanie",
        "files": [
            {
                "id": "F09BUNSH6S2",
                "created": 1756049829,
                "timestamp": 1756049829,
                "name": "IMG_1736.jpg",
                "title": "IMG_1736",
                "mimetype": "image\/jpeg",
                "filetype": "jpg",
                "pretty_type": "JPEG",
                "user": "U04Q6BMSJER",
                "user_team": "T0P9KU8UD",
                "editable": false,
                "size": 676774,
                "mode": "hosted",
                "is_external": false,
                "external_type": "",
                "is_public": true,
                "public_url_shared": false,
                "display_as_bot": false,
                "username": "",
                "url_private": "https:\/\/files.slack.com\/files-pri\/T0P9KU8UD-F09BUNSH6S2\/img_1736.jpg?token=xoxe-23325960965-9983715179761-9964412545267-7f7e21946507533879d0107de1674c00",
                "url_private_download": "https:\/\/files.slack.com\/files-pri\/T0P9KU8UD-F09BUNSH6S2\/download\/img_1736.jpg?token=xoxe-23325960965-9983715179761-9964412545267-7f7e21946507533879d0107de1674c00",
                "media_display_type": "unknown",
                "thumb_64": "https:\/\/files.slack.com\/files-tmb\/T0P9KU8UD-F09BUNSH6S2-8c0129bd3b\/img_1736_64.jpg?t=xoxe-23325960965-9983715179761-9964412545267-7f7e21946507533879d0107de1674c00",
                "thumb_80": "https:\/\/files.slack.com\/files-tmb\/T0P9KU8UD-F09BUNSH6S2-8c0129bd3b\/img_1736_80.jpg?t=xoxe-23325960965-9983715179761-9964412545267-7f7e21946507533879d0107de1674c00",
                "thumb_360": "https:\/\/files.slack.com\/files-tmb\/T0P9KU8UD-F09BUNSH6S2-8c0129bd3b\/img_1736_360.jpg?t=xoxe-23325960965-9983715179761-9964412545267-7f7e21946507533879d0107de1674c00",
                "thumb_360_w": 270,
                "thumb_360_h": 360,
                "thumb_480": "https:\/\/files.slack.com\/files-tmb\/T0P9KU8UD-F09BUNSH6S2-8c0129bd3b\/img_1736_480.jpg?t=xoxe-23325960965-9983715179761-9964412545267-7f7e21946507533879d0107de1674c00",
                "thumb_480_w": 360,
                "thumb_480_h": 480,
                "thumb_160": "https:\/\/files.slack.com\/files-tmb\/T0P9KU8UD-F09BUNSH6S2-8c0129bd3b\/img_1736_160.jpg?t=xoxe-23325960965-9983715179761-9964412545267-7f7e21946507533879d0107de1674c00",
                "thumb_720": "https:\/\/files.slack.com\/files-tmb\/T0P9KU8UD-F09BUNSH6S2-8c0129bd3b\/img_1736_720.jpg?t=xoxe-23325960965-9983715179761-9964412545267-7f7e21946507533879d0107de1674c00",
                "thumb_720_w": 540,
                "thumb_720_h": 720,
                "thumb_800": "https:\/\/files.slack.com\/files-tmb\/T0P9KU8UD-F09BUNSH6S2-8c0129bd3b\/img_1736_800.jpg?t=xoxe-23325960965-9983715179761-9964412545267-7f7e21946507533879d0107de1674c00",
                "thumb_800_w": 800,
                "thumb_800_h": 1067,
                "thumb_960": "https:\/\/files.slack.com\/files-tmb\/T0P9KU8UD-F09BUNSH6S2-8c0129bd3b\/img_1736_960.jpg?t=xoxe-23325960965-9983715179761-9964412545267-7f7e21946507533879d0107de1674c00",
                "thumb_960_w": 720,
                "thumb_960_h": 960,
                "thumb_1024": "https:\/\/files.slack.com\/files-tmb\/T0P9KU8UD-F09BUNSH6S2-8c0129bd3b\/img_1736_1024.jpg?t=xoxe-23325960965-9983715179761-9964412545267-7f7e21946507533879d0107de1674c00",
                "thumb_1024_w": 768,
                "thumb_1024_h": 1024,
                "original_w": 3024,
                "original_h": 4032,
                "thumb_tiny": "AwAwACSGJQ7M8wJ75HGTUrTK8xwdxI3HHT6e\/wDkUskZkXG\/YB1qOBYosgujN6g8UhlmAFnU5yAuRx0zUF0cliVJGcY7cVZtyo8xh6Z49KilXFiD6tmklcCm+C7EDjPam49qkSPO489TT\/J9z+lUIrGRmBBJ596QAk4xzSgc1aRQuGx1HNJjWo23d4gVPRwRUszDCoW4PUemP8mnHBOMZPBGB0\/zzUciuDtfPUkD2zST1HYQrz8uQKNh9TVqJMpyelP8sVQjLt4zI4HYVoyxjacgY9aoQyrHyc5q2l2kpKHKgjAJ9aQDS4BCkHLDnPpml\/1km49KaF3uDjoMUTSBB5S\/ePU+lSiiRU3DcVBz69qXyx\/cX8qo3rfvgP7qgf1qtmqsLmP\/2Q==",
                "permalink": "https:\/\/cornelldti.slack.com\/files\/UNZJ5EE3A\/F09BUNSH6S2\/img_1736.jpg",
                "permalink_public": "https:\/\/slack-files.com\/T0P9KU8UD-F09BUNSH6S2-000cae55c2",
                "is_starred": false,
                "skipped_shares": true,
                "has_rich_preview": false,
                "file_access": "visible"
            }
        ],
        "upload": false,
        "user": "U04Q6BMSJER",
        "display_as_bot": false,
        "blocks": [
            {
                "type": "rich_text",
                "block_id": "bqOX2",
                "elements": [
                    {
                        "type": "rich_text_section",
                        "elements": [
                            {
                                "type": "text",
                                "text": "methinks this is "
                            },
                            {
                                "type": "user",
                                "user_id": "U080M7935R6"
                            },
                            {
                                "type": "text",
                                "text": " "
                            },
                            {
                                "type": "text",
                                "text": "no beanie"
                            }
                        ]
                    }
                ]
            }
        ],
        "type": "message",
        "ts": "1756049862.863069",
        "client_msg_id": "563199FF-A9EB-4D72-838F-DB082F12BF12",
        "reactions": [
            {
                "name": "melting_face",
                "users": [
                    "U080M7935R6",
                    "U07USUF040P",
                    "U080G6QDZT2"
                ],
                "count": 3
            }
        ]
    },
    {
        "text": "<@U04Q99S2Y3C> <@U06K2TZALJ2>",
        "files": [
            {
                "id": "F09C6PS7L9F",
                "created": 1756058683,
                "timestamp": 1756058683,
                "name": "1000016492.jpg",
                "title": "1000016492.jpg",
                "mimetype": "image\/jpeg",
                "filetype": "jpg",
                "pretty_type": "JPEG",
                "user": "U07V0PDSY78",
                "user_team": "T0P9KU8UD",
                "editable": false,
                "size": 389563,
                "mode": "hosted",
                "is_external": false,
                "external_type": "",
                "is_public": true,
                "public_url_shared": false,
                "display_as_bot": false,
                "username": "",
                "url_private": "https:\/\/files.slack.com\/files-pri\/T0P9KU8UD-F09C6PS7L9F\/1000016492.jpg?token=xoxe-23325960965-9983715179761-9964412545267-7f7e21946507533879d0107de1674c00",
                "url_private_download": "https:\/\/files.slack.com\/files-pri\/T0P9KU8UD-F09C6PS7L9F\/download\/1000016492.jpg?token=xoxe-23325960965-9983715179761-9964412545267-7f7e21946507533879d0107de1674c00",
                "media_display_type": "unknown",
                "thumb_64": "https:\/\/files.slack.com\/files-tmb\/T0P9KU8UD-F09C6PS7L9F-026e056379\/1000016492_64.jpg?t=xoxe-23325960965-9983715179761-9964412545267-7f7e21946507533879d0107de1674c00",
                "thumb_80": "https:\/\/files.slack.com\/files-tmb\/T0P9KU8UD-F09C6PS7L9F-026e056379\/1000016492_80.jpg?t=xoxe-23325960965-9983715179761-9964412545267-7f7e21946507533879d0107de1674c00",
                "thumb_360": "https:\/\/files.slack.com\/files-tmb\/T0P9KU8UD-F09C6PS7L9F-026e056379\/1000016492_360.jpg?t=xoxe-23325960965-9983715179761-9964412545267-7f7e21946507533879d0107de1674c00",
                "thumb_360_w": 271,
                "thumb_360_h": 360,
                "thumb_480": "https:\/\/files.slack.com\/files-tmb\/T0P9KU8UD-F09C6PS7L9F-026e056379\/1000016492_480.jpg?t=xoxe-23325960965-9983715179761-9964412545267-7f7e21946507533879d0107de1674c00",
                "thumb_480_w": 361,
                "thumb_480_h": 480,
                "thumb_160": "https:\/\/files.slack.com\/files-tmb\/T0P9KU8UD-F09C6PS7L9F-026e056379\/1000016492_160.jpg?t=xoxe-23325960965-9983715179761-9964412545267-7f7e21946507533879d0107de1674c00",
                "thumb_720": "https:\/\/files.slack.com\/files-tmb\/T0P9KU8UD-F09C6PS7L9F-026e056379\/1000016492_720.jpg?t=xoxe-23325960965-9983715179761-9964412545267-7f7e21946507533879d0107de1674c00",
                "thumb_720_w": 542,
                "thumb_720_h": 720,
                "thumb_800": "https:\/\/files.slack.com\/files-tmb\/T0P9KU8UD-F09C6PS7L9F-026e056379\/1000016492_800.jpg?t=xoxe-23325960965-9983715179761-9964412545267-7f7e21946507533879d0107de1674c00",
                "thumb_800_w": 800,
                "thumb_800_h": 1063,
                "thumb_960": "https:\/\/files.slack.com\/files-tmb\/T0P9KU8UD-F09C6PS7L9F-026e056379\/1000016492_960.jpg?t=xoxe-23325960965-9983715179761-9964412545267-7f7e21946507533879d0107de1674c00",
                "thumb_960_w": 723,
                "thumb_960_h": 960,
                "thumb_1024": "https:\/\/files.slack.com\/files-tmb\/T0P9KU8UD-F09C6PS7L9F-026e056379\/1000016492_1024.jpg?t=xoxe-23325960965-9983715179761-9964412545267-7f7e21946507533879d0107de1674c00",
                "thumb_1024_w": 771,
                "thumb_1024_h": 1024,
                "original_w": 3072,
                "original_h": 4080,
                "thumb_tiny": "AwAwACWUACV4uemeelCghQG+93qE8SZLsG75BFSqcjrn3qSh1NPalpCcEZ9aAIn+8aSiVQ7dCR2pnlL\/AHT+tUIcXb+8eRjmhXYcA8D2pB16Z\/SkAyrd8c4oESLKx\/u479aAAWYuTu6Ag9qizx70jMRGv7wLye3WiwFsMqouKPMFVi7sBsce+AKTM398flSsVcXkHvSopwc8Z\/xqQKBg4pjMeQFPB6g1RAuFXIPeo3C8DC49OtBLHsaMeuc\/SgYgO0YCgfhS7z6D8qBgd\/0oyPb8qQH\/2Q==",
                "permalink": "https:\/\/cornelldti.slack.com\/files\/UNZJ5EE3A\/F09C6PS7L9F\/1000016492.jpg",
                "permalink_public": "https:\/\/slack-files.com\/T0P9KU8UD-F09C6PS7L9F-afa43eb20a",
                "is_starred": false,
                "skipped_shares": true,
                "has_rich_preview": false,
                "file_access": "visible"
            }
        ],
        "upload": false,
        "user": "U07V0PDSY78",
        "display_as_bot": false,
        "blocks": [
            {
                "type": "rich_text",
                "block_id": "5gwTE",
                "elements": [
                    {
                        "type": "rich_text_section",
                        "elements": [
                            {
                                "type": "user",
                                "user_id": "U04Q99S2Y3C"
                            },
                            {
                                "type": "text",
                                "text": " "
                            },
                            {
                                "type": "user",
                                "user_id": "U06K2TZALJ2"
                            }
                        ]
                    }
                ]
            }
        ],
        "type": "message",
        "ts": "1756058694.776549",
        "client_msg_id": "76970a55-bf8f-4ff5-a613-56d4601bd626",
        "reactions": [
            {
                "name": "bangbang",
                "users": [
                    "U0806411Z5X"
                ],
                "count": 1
            }
        ]
    },
    {
        "text": "<@U07USUF040P> and <@U080G5L9MTJ> I think :laughing:",
        "files": [
            {
                "id": "F09BWSXULUC",
                "created": 1756058962,
                "timestamp": 1756058962,
                "name": "IMG20250824140853.jpg",
                "title": "IMG20250824140853.jpg",
                "mimetype": "image\/jpeg",
                "filetype": "jpg",
                "pretty_type": "JPEG",
                "user": "U06KC1WG86Q",
                "user_team": "T0P9KU8UD",
                "editable": false,
                "size": 1515056,
                "mode": "hosted",
                "is_external": false,
                "external_type": "",
                "is_public": true,
                "public_url_shared": false,
                "display_as_bot": false,
                "username": "",
                "url_private": "https:\/\/files.slack.com\/files-pri\/T0P9KU8UD-F09BWSXULUC\/img20250824140853.jpg?token=xoxe-23325960965-9983715179761-9964412545267-7f7e21946507533879d0107de1674c00",
                "url_private_download": "https:\/\/files.slack.com\/files-pri\/T0P9KU8UD-F09BWSXULUC\/download\/img20250824140853.jpg?token=xoxe-23325960965-9983715179761-9964412545267-7f7e21946507533879d0107de1674c00",
                "media_display_type": "unknown",
                "thumb_64": "https:\/\/files.slack.com\/files-tmb\/T0P9KU8UD-F09BWSXULUC-39ee185aa1\/img20250824140853_64.jpg?t=xoxe-23325960965-9983715179761-9964412545267-7f7e21946507533879d0107de1674c00",
                "thumb_80": "https:\/\/files.slack.com\/files-tmb\/T0P9KU8UD-F09BWSXULUC-39ee185aa1\/img20250824140853_80.jpg?t=xoxe-23325960965-9983715179761-9964412545267-7f7e21946507533879d0107de1674c00",
                "thumb_360": "https:\/\/files.slack.com\/files-tmb\/T0P9KU8UD-F09BWSXULUC-39ee185aa1\/img20250824140853_360.jpg?t=xoxe-23325960965-9983715179761-9964412545267-7f7e21946507533879d0107de1674c00",
                "thumb_360_w": 270,
                "thumb_360_h": 360,
                "thumb_480": "https:\/\/files.slack.com\/files-tmb\/T0P9KU8UD-F09BWSXULUC-39ee185aa1\/img20250824140853_480.jpg?t=xoxe-23325960965-9983715179761-9964412545267-7f7e21946507533879d0107de1674c00",
                "thumb_480_w": 360,
                "thumb_480_h": 480,
                "thumb_160": "https:\/\/files.slack.com\/files-tmb\/T0P9KU8UD-F09BWSXULUC-39ee185aa1\/img20250824140853_160.jpg?t=xoxe-23325960965-9983715179761-9964412545267-7f7e21946507533879d0107de1674c00",
                "thumb_720": "https:\/\/files.slack.com\/files-tmb\/T0P9KU8UD-F09BWSXULUC-39ee185aa1\/img20250824140853_720.jpg?t=xoxe-23325960965-9983715179761-9964412545267-7f7e21946507533879d0107de1674c00",
                "thumb_720_w": 540,
                "thumb_720_h": 720,
                "thumb_800": "https:\/\/files.slack.com\/files-tmb\/T0P9KU8UD-F09BWSXULUC-39ee185aa1\/img20250824140853_800.jpg?t=xoxe-23325960965-9983715179761-9964412545267-7f7e21946507533879d0107de1674c00",
                "thumb_800_w": 800,
                "thumb_800_h": 1067,
                "thumb_960": "https:\/\/files.slack.com\/files-tmb\/T0P9KU8UD-F09BWSXULUC-39ee185aa1\/img20250824140853_960.jpg?t=xoxe-23325960965-9983715179761-9964412545267-7f7e21946507533879d0107de1674c00",
                "thumb_960_w": 720,
                "thumb_960_h": 960,
                "thumb_1024": "https:\/\/files.slack.com\/files-tmb\/T0P9KU8UD-F09BWSXULUC-39ee185aa1\/img20250824140853_1024.jpg?t=xoxe-23325960965-9983715179761-9964412545267-7f7e21946507533879d0107de1674c00",
                "thumb_1024_w": 768,
                "thumb_1024_h": 1024,
                "original_w": 3072,
                "original_h": 4096,
                "thumb_tiny": "AwAwACR4p6NgYOcH0puMUoFaECSRJKcsOfUcGqctu6H5QWHqBWiE4znJ9qSkMzPJk7RP\/wB8mjyZf+eUn\/fJrVBPrijJ\/vD8qVgKAu3CjcATSm6YtwAB9c1H5KSY8tvwxUgtBjBwcA89Pw71N2VYnjuYy4UMOn3sYGaS6uCq4j55HOc0xLWPbgt+nUU820RAGT7cUXCxQkkZm+YnI455pu\/3\/Sr\/ANjQknJ69gB\/Sj7HH6t+n+FADYQRI5K4BPGfxqXgYyRnH4Umz0J59+9LsUcbjgdck0hjgBnO7\/61KRx3x7UwIAOASCP7xNOHUUAO\/ED680n\/AAJfypC5HAI4pN7\/AN4UAf\/Z",
                "permalink": "https:\/\/cornelldti.slack.com\/files\/UNZJ5EE3A\/F09BWSXULUC\/img20250824140853.jpg",
                "permalink_public": "https:\/\/slack-files.com\/T0P9KU8UD-F09BWSXULUC-7990ca51b8",
                "is_starred": false,
                "skipped_shares": true,
                "has_rich_preview": false,
                "file_access": "visible"
            }
        ],
        "upload": false,
        "user": "U06KC1WG86Q",
        "display_as_bot": false,
        "blocks": [
            {
                "type": "rich_text",
                "block_id": "O6AFB",
                "elements": [
                    {
                        "type": "rich_text_section",
                        "elements": [
                            {
                                "type": "user",
                                "user_id": "U07USUF040P"
                            },
                            {
                                "type": "text",
                                "text": " and "
                            },
                            {
                                "type": "user",
                                "user_id": "U080G5L9MTJ"
                            },
                            {
                                "type": "text",
                                "text": " I think "
                            },
                            {
                                "type": "emoji",
                                "name": "laughing",
                                "unicode": "1f606"
                            }
                        ]
                    }
                ]
            }
        ],
        "type": "message",
        "ts": "1756058985.405059",
        "client_msg_id": "1e75ed48-e5d1-4aac-880c-4d861e49b3df",
        "reactions": [
            {
                "name": "sob",
                "users": [
                    "U07USUF040P",
                    "U0806411Z5X",
                    "U080G5L9MTJ"
                ],
                "count": 3
            }
        ]
    }
]